fincallibsfiles/__init__.py
fincallibsfiles/abhi_hello.py
fina_cal_abhi-0.0.3.dist-info/METADATA
fina_cal_abhi-0.0.3.dist-info/WHEEL
fina_cal_abhi-0.0.3.dist-info/top_level.txt
fina_cal_abhi-0.0.3.dist-info/RECORD
