Metadata-Version: 2.1
Name: fina-cal-abhi
Version: 0.0.3
Summary: A finance calculation package
Author: Abhishek Vyas
Author-email: abhishek.vyas@gmail.com
License: NEXT
Keywords: finance-calculation
